openalgo_mcp/__init__.py
openalgo_mcp/mcpserver.py
openalgo_mcp-0.1.8.dist-info/METADATA
openalgo_mcp-0.1.8.dist-info/WHEEL
openalgo_mcp-0.1.8.dist-info/entry_points.txt
openalgo_mcp-0.1.8.dist-info/top_level.txt
openalgo_mcp-0.1.8.dist-info/RECORD
