Metadata-Version: 2.4
Name: openalgo-mcp
Version: 0.1.8
Summary: OpenAlgo MCP Server stub
Project-URL: Homepage, https://github.com/p2c2e/openalgo_mcp
Project-URL: Repository, https://github.com/p2c2e/openalgo_mcp
Requires-Python: >=3.12
Requires-Dist: fastmcp>=2.11.2
Requires-Dist: httpx[http2]>=0.28.1
Requires-Dist: mcp>=1.12.3
Requires-Dist: nest-asyncio>=1.6.0
